{
  "items": {
    "capacity": {
      "ease": 2.6,
      "interval": 1,
      "reps": 1,
      "lapses": 0,
      "due": 1780200996257,
      "lastReview": 1780114596257
    },
    "track": {
      "ease": 2.6,
      "interval": 1,
      "reps": 1,
      "lapses": 0,
      "due": 1780201003377,
      "lastReview": 1780114603377
    },
    "destruction": {
      "ease": 2.6,
      "interval": 1,
      "reps": 1,
      "lapses": 0,
      "due": 1780203281147,
      "lastReview": 1780116881147
    },
    "exposes": {
      "ease": 2.6,
      "interval": 1,
      "reps": 1,
      "lapses": 0,
      "due": 1780203326028,
      "lastReview": 1780116926028
    },
    "consistent": {
      "ease": 2.6,
      "interval": 1,
      "reps": 1,
      "lapses": 0,
      "due": 1780203329769,
      "lastReview": 1780116929769
    },
    "unknown": {
      "ease": 2.6,
      "interval": 1,
      "reps": 1,
      "lapses": 0,
      "due": 1780203333908,
      "lastReview": 1780116933908
    },
    "anticipation": {
      "ease": 2.6,
      "interval": 1,
      "reps": 1,
      "lapses": 0,
      "due": 1780216712291,
      "lastReview": 1780130312291
    },
    "backfire": {
      "ease": 2.6,
      "interval": 1,
      "reps": 1,
      "lapses": 0,
      "due": 1780216739873,
      "lastReview": 1780130339873
    },
    "monetary": {
      "ease": 2.6,
      "interval": 1,
      "reps": 1,
      "lapses": 0,
      "due": 1780216789709,
      "lastReview": 1780130389709
    }
  }
}